huaweicloudsdkworkspaceapp/__init__.py
huaweicloudsdkworkspaceapp/v1/__init__.py
huaweicloudsdkworkspaceapp/v1/workspaceapp_async_client.py
huaweicloudsdkworkspaceapp/v1/workspaceapp_client.py
huaweicloudsdkworkspaceapp/v1/model/__init__.py
huaweicloudsdkworkspaceapp/v1/model/account_info.py
huaweicloudsdkworkspaceapp/v1/model/account_type_enum.py
huaweicloudsdkworkspaceapp/v1/model/add_app_group_authorization_request.py
huaweicloudsdkworkspaceapp/v1/model/add_app_group_authorization_response.py
huaweicloudsdkworkspaceapp/v1/model/add_volumes.py
huaweicloudsdkworkspaceapp/v1/model/app.py
huaweicloudsdkworkspaceapp/v1/model/app_category_enum.py
huaweicloudsdkworkspaceapp/v1/model/app_connection_info.py
huaweicloudsdkworkspaceapp/v1/model/app_extended_info.py
huaweicloudsdkworkspaceapp/v1/model/app_group.py
huaweicloudsdkworkspaceapp/v1/model/app_group_authorize_req.py
huaweicloudsdkworkspaceapp/v1/model/app_server.py
huaweicloudsdkworkspaceapp/v1/model/app_server_status.py
huaweicloudsdkworkspaceapp/v1/model/app_server_task_status.py
huaweicloudsdkworkspaceapp/v1/model/app_session.py
huaweicloudsdkworkspaceapp/v1/model/app_state_enum.py
huaweicloudsdkworkspaceapp/v1/model/app_type_enum.py
huaweicloudsdkworkspaceapp/v1/model/assign_share_folder_req.py
huaweicloudsdkworkspaceapp/v1/model/assign_user_folder_req.py
huaweicloudsdkworkspaceapp/v1/model/assignment.py
huaweicloudsdkworkspaceapp/v1/model/attach_image_server_app_request.py
huaweicloudsdkworkspaceapp/v1/model/attach_image_server_app_response.py
huaweicloudsdkworkspaceapp/v1/model/attach_server_app_info.py
huaweicloudsdkworkspaceapp/v1/model/attach_server_app_req.py
huaweicloudsdkworkspaceapp/v1/model/attach_type.py
huaweicloudsdkworkspaceapp/v1/model/attachment.py
huaweicloudsdkworkspaceapp/v1/model/authorization.py
huaweicloudsdkworkspaceapp/v1/model/authorization_mail.py
huaweicloudsdkworkspaceapp/v1/model/authorization_type_enum.py
huaweicloudsdkworkspaceapp/v1/model/authorize_obs_req.py
huaweicloudsdkworkspaceapp-3.1.184.dist-info/METADATA
huaweicloudsdkworkspaceapp-3.1.184.dist-info/WHEEL
huaweicloudsdkworkspaceapp-3.1.184.dist-info/licenses/LICENSE
huaweicloudsdkworkspaceapp-3.1.184.dist-info/RECORD
